careers/__init__.py
careers/admin.py
careers/models.py
careers/urls.py
careers/views.py
careers/migrations/0001_initial.py
careers/migrations/__init__.py
careers/static/.empty
careers/static/careers/.empty
careers/templates/careers/careers_desc.html
careers/templates/careers/careers_list_item.html
careers/templates/careers/careers_list_view.html
careers/templates/careers/careers_view.html
careers/tests/__init__.py
careers/tests/models_tests.py
careers/tests/settings.py
careers/tests/test_settings.py
careers/tests/urls.py
careers/tests/views_tests.py
careers/tests/test_app/__init__.py
careers/tests/test_app/models.py
careers/tests/test_app/templates/400.html
careers/tests/test_app/templates/500.html
careers/tests/test_app/templates/base.html
django_careers-0.1.6.dist-info/DESCRIPTION.rst
django_careers-0.1.6.dist-info/METADATA
django_careers-0.1.6.dist-info/RECORD
django_careers-0.1.6.dist-info/WHEEL
django_careers-0.1.6.dist-info/metadata.json
django_careers-0.1.6.dist-info/top_level.txt
