Metadata-Version: 2.0
Name: django-careers
Version: 0.1.6
Summary: A simple app to render a careers-page on your website.
Requires-Dist: django (>=1.8)
Requires-Dist: django-markdown-app (==0.8.6)
Provides-Extra: dev
Requires-Dist: flake8; extra == 'dev'
